alphaavatar/plugins/rag/__init__.py
alphaavatar/plugins/rag/log.py
alphaavatar/plugins/rag/rag_anything.py
alphaavatar/plugins/rag/version.py
alpha_avatar_plugins_rag-0.4.0.dist-info/METADATA
alpha_avatar_plugins_rag-0.4.0.dist-info/WHEEL
alpha_avatar_plugins_rag-0.4.0.dist-info/RECORD
