Metadata-Version: 2.4
Name: alpha-avatar-plugins-rag
Version: 0.4.0
Summary: AlphaAvatar Framework plugin for RAG service
Project-URL: Source, https://github.com/AlphaAvatar/AlphaAvatar
License-Expression: Apache-2.0
Keywords: AI,agents,internet,llm,multimodel,rag
Classifier: Intended Audience :: Developers
Classifier: License :: OSI Approved :: Apache Software License
Classifier: Programming Language :: Python :: 3
Classifier: Programming Language :: Python :: 3 :: Only
Classifier: Programming Language :: Python :: 3.10
Classifier: Programming Language :: Python :: 3.11
Classifier: Programming Language :: Python :: 3.12
Classifier: Programming Language :: Python :: 3.13
Classifier: Topic :: Multimedia :: Sound/Audio
Classifier: Topic :: Multimedia :: Video
Classifier: Topic :: Scientific/Engineering :: Artificial Intelligence
Requires-Python: >=3.10
Requires-Dist: docling
Requires-Dist: raganything[all]
